[
	{
		"id": "geral",
		"image": "https://api.adorable.io/avatars/285/@adorable.io.png",
		"name": "Geral",
		"title": "Geral",
		"describe": "Deste sorteio participam todos colaboradores.",
		"blacklist": [],
		"winners":[],
		"awards": [
			{
				"image": "camera_instax.jpg",
				"name": "CÂMERA INSTANTÂNEA INSTAX MINI"
			},
			{
				"image": "chopeira.jpg",
				"name": "CHOPEIRA BEERTENDER HEINEKEN"
			},
			{
				"image": "miband.jpg",
				"name": "SMARTWATCH XIAOMI MI BAND 4"
			},
			{
				"image": "playstation.png",
				"name": "PLAYSTATION 4 SLIM + 01 CONTROLE"
			},
			{
				"image": "echodot.jpg",
				"name": "ECHO DOT (4ª GERAÇÃO) SMART SPEAKER COM ALEXA"
			},
			{
				"image": "tv32.png",
				"name": "SMART TV LED 32\""
			}
		]
	},
	{
		"id": "delivery",
		"image": "https://api.adorable.io/avatars/285/fl@adorable.io.png",
		"name": "Delivery Direto",
		"title": "Delivery Direto",
		"describe": "Deste sorteio participam todos colaboradores da Delivery Direto.",
		"blacklist": [],
		"winners":[],
		"awards": [
			{
				"image": "caixa_jbl.png",
				"name": "CAIXA DE SOM JBL"
			}
		]
	},
	{
		"id": "etus",
		"image": "https://api.adorable.io/avatars/285/fl@adorable.io.png",
		"name": "Etus",
		"title": "Etus",
		"describe": "Deste sorteio participam todos colaboradores da Etus.",
		"blacklist": [],
		"winners":[],
		"awards": [
			{
				"image": "panela_pressao.jpg",
				"name": "PANELA DE PRESSÃO ELÉTRICA MONDIAL PRATIC COOK"
			}
		]
	},
	{
		"id": "kinghost",
		"image": "https://api.adorable.io/avatars/285/fl@adorable.io.png",
		"name": "King Host",
		"title": "King Host",
		"describe": "Deste sorteio participam todos colaboradores da King Host.",
		"blacklist": [],
		"winners":[],
		"awards": [
			{
				"image": "redminote8.jpg",
				"name": "SMARTPHONE XIAOMI REDMI NOTE 8"
			},
			{
				"image": "chopeira.jpg",
				"name": "CHOPEIRA BEERTENDER HEINEKEN"
			}
		]
	},
	{
		"id": "locawebcommerce",
		"image": "https://api.adorable.io/avatars/285/fl@adorable.io.png",
		"name": "Locaweb Commerce",
		"title": "Locaweb Commerce",
		"describe": "Deste sorteio participam todos colaboradores Locaweb Commerce.",
		"blacklist": [],
		"winners":[],
		"awards": [
			{
				"image": "chopeira.jpg",
				"name": "CHOPEIRA BEERTENDER HEINEKEN"
			},
			{
				"image": "tv32.png",
				"name": "SMART TV LED 32\""
			},
			{
				"image": "nespresso.jpg",
				"name": "MÁQUINA DE CAFÉ NESPRESSO ESSENZA MINI"
			}
		]
	},
	{
		"id": "socialminer",
		"image": "https://api.adorable.io/avatars/285/fl@adorable.io.png",
		"name": "Social Miner",
		"title": "Social Miner",
		"describe": "Deste sorteio participam todos colaboradores da Social Miner.",
		"blacklist": [],
		"winners":[],
		"awards": [
			{
				"image": "kindle.jpg",
				"name": "KINDLE PAPERWHITE 8 GB"
			}
		]
	},
	{
		"id": "valeu",
		"image": "https://api.adorable.io/avatars/285/joe@adorable.io.png",
		"name": "Valeu",
		"title": "Cartão Valeu",
		"describe": "Deste sorteio participam todos colaboradores que ganharam o valeu.",
		"blacklist": [],
		"winners":[],
		"awards": [
			{
				"image": "ecodot.png",
				"name": "ECHO DOT (4ª GERAÇÃO) SMART SPEAKER COM ALEXA"
			},
			{
				"image": "adega.jpg",
				"name": "ADEGA BRASTEMP 12 GARRAFAS COM PAINEL TOUCH "
			},
			{
				"image": "churrasqueira.jpg",
				"name": "CHURRASQUEIRA STEAKHOUSE GRILL POLISHOP"
			},
			{
				"image": "playstation.png",
				"name": "PLAYSTATION 4 SLIM + 01 CONTROLE"
			},
			{
				"image": "aspirador.jpg",
				"name": "ASPIRADOR DE PÓ ROBÔ WAP ROBOT W300"
			}
		]
	},
	{
		"id": "surpresa",
		"image": "https://api.adorable.io/avatars/285/fl@adorable.io.png",
		"name": "Surpresa",
		"title": "Surpresa",
		"describe": "Deste sorteio participam todos colaboradores da Surpresa.",
		"blacklist": [],
		"winners":[],
		"awards": [
			{
				"image": "gopro.svg",
				"name": "Câmera Digital GoPro Hero7"
			},
			{
				"image": "churrasco.svg",
				"name": "Kit para churrasco Tramontina"
			}
		]
	},
	{
		"id": "pratas",
		"image": "https://api.adorable.io/avatars/285/bob@adorable.io.png",
		"name": "Pratas da Casa",
		"title": "Pratas da Casa",
		"describe": "Deste sorteio participam todos colaboradores pratas da casa.",
		"blacklist": [],
		"winners":[],
		"awards": [
			{
				"image": "motorola.svg",
				"name": "Smartphone Motorola"
			},
			{
				"image": "instax.svg",
				"name": "Câmera Instantânea Instax Mini"
			},
			{
				"image": "chopeira.svg",
				"name": "Chopeira Beertender Heineken"
			}
		]
	},
	{
		"id": "conexao",
		"image": "https://api.adorable.io/avatars/285/joe@adorable.io.png",
		"name": "Conexão Saúde",
		"title": "Conexão Saúde",
		"describe": "Deste sorteio participam todos colaboradores que participaram do conexão saúde.",
		"blacklist": [],
		"winners":[],
		"awards": [
			{
				"image": "airfryer.svg",
				"name": "Air Fryer"
			},
			{
				"image": "pao.svg",
				"name": "Máquina de Pão"
			},
			{
				"image": "airfryer.svg",
				"name": "Air Fryer"
			}
		]
	},
	{
		"id": "presenciais",
		"image": "https://api.adorable.io/avatars/285/fl@adorable.io.png",
		"name": "Presenciais",
		"title": "Presenciais",
		"describe": "Deste sorteio participam todos colaboradores da Presenciais.",
		"blacklist": [],
		"winners":[],
		"awards": [
			{
				"image": "gopro.svg",
				"name": "Câmera Digital GoPro Hero7"
			},
			{
				"image": "churrasco.svg",
				"name": "Kit para churrasco Tramontina"
			}
		]
	},
	{
		"id": "karaoke",
		"image": "https://api.adorable.io/avatars/285/fl@adorable.io.png",
		"name": "Karaokê",
		"title": "Karaokê",
		"describe": "Deste sorteio participam todos que fizeram parte do Karaokê.",
		"blacklist": [],
		"winners":[],
		"awards": [
			{
				"image": "gopro.svg",
				"name": "Câmera Digital GoPro Hero7"
			},
			{
				"image": "churrasco.svg",
				"name": "Kit para churrasco Tramontina"
			}
		]
	}
]